nkit/__init__.py
nkit/constants.py
nkit/exceptions.py
nkit/main.py
nkit/models.py
nkit/notes_app.py
nkit/storage/__init__.py
nkit/storage/local.py
nkit/storage/storage.py
nkit/sync_app.py
nkit/types.py
nkit/utils.py
nkit-0.1.2.dist-info/entry_points.txt
nkit-0.1.2.dist-info/LICENSE
nkit-0.1.2.dist-info/WHEEL
nkit-0.1.2.dist-info/METADATA
nkit-0.1.2.dist-info/RECORD
