Metadata-Version: 2.1
Name: nkit
Version: 0.1.2
Summary: 
License: MIT
Author: Ankit
Author-email: ankitsaini100205@gmail.com
Requires-Python: >=3.6,<4.0
Classifier: License :: OSI Approved :: MIT License
Classifier: Programming Language :: Python :: 3
Classifier: Programming Language :: Python :: 3.6
Classifier: Programming Language :: Python :: 3.7
Classifier: Programming Language :: Python :: 3.8
Classifier: Programming Language :: Python :: 3.9
Requires-Dist: arrow (>=0.17.0,<0.18.0)
Requires-Dist: dataset (>=1.3.2,<2.0.0)
Requires-Dist: httpx (>=0.16.1,<0.17.0)
Requires-Dist: pydantic (>=1.7.2,<2.0.0)
Requires-Dist: typer[all] (>=0.3.2,<0.4.0)
